cardscan/__init__.py
cardscan/image_processing/__init__.py
cardscan/image_processing/colors.py
cardscan/image_processing/contour_hierarchy.py
cardscan/image_processing/frame_contour.py
cardscan/image_processing/transforms.py
cardscan/pipeline/__init__.py
cardscan/pipeline/pipeline.py
cardscan/pipeline_instances/__init__.py
cardscan/pipeline_instances/display_transforms.py
cardscan/pipeline_instances/rect_perspective_pipeline.py
cardscan/visualize/__init__.py
cardscan/visualize/cam_app.py
cardscan/visualize/draw_pip_app.py
cardscan/visualize/helper.py
cardscan/visualize/tile_gallery.py
cardscan-0.4.0.dist-info/METADATA
cardscan-0.4.0.dist-info/WHEEL
cardscan-0.4.0.dist-info/RECORD
