Metadata-Version: 2.1
Name: cardscan
Version: 0.4.0
Summary: OpenCV python pipeline to finds black bordered frame in an image. Fix the perspective, crop and rotate.
License: MIT
Author: Félix JULLIEN
Author-email: jullienfelix@gmail.com
Requires-Python: >=3.10,<4.0
Classifier: License :: OSI Approved :: MIT License
Classifier: Programming Language :: Python :: 3
Classifier: Programming Language :: Python :: 3.10
Classifier: Programming Language :: Python :: 3.11
Requires-Dist: numpy (>=1.25.2,<2.0.0)
Requires-Dist: opencv-python (>=4.8.0.76,<5.0.0.0)
